gocept.filestore-1.0-py3.11-nspkg.pth
gocept/filestore/README.txt
gocept/filestore/__init__.py
gocept/filestore/filestore.py
gocept/filestore/interfaces.py
gocept/filestore/tests.py
gocept.filestore-1.0.dist-info/LICENSE.txt
gocept.filestore-1.0.dist-info/METADATA
gocept.filestore-1.0.dist-info/WHEEL
gocept.filestore-1.0.dist-info/namespace_packages.txt
gocept.filestore-1.0.dist-info/top_level.txt
gocept.filestore-1.0.dist-info/RECORD
